b_lambda_layer_common/__init__.py
b_lambda_layer_common/api_gateway/__init__.py
b_lambda_layer_common/api_gateway/api_key.py
b_lambda_layer_common/api_gateway/body.py
b_lambda_layer_common/api_gateway/cognito_access_token.py
b_lambda_layer_common/api_gateway/exception_middleware.py
b_lambda_layer_common/api_gateway/neighbour_endpoint.py
b_lambda_layer_common/api_gateway/remove_header.py
b_lambda_layer_common/api_gateway/response.py
b_lambda_layer_common/api_gateway/response_headers.py
b_lambda_layer_common/api_gateway/url.py
b_lambda_layer_common/cache/__init__.py
b_lambda_layer_common/cache/in_memory_data_cache.py
b_lambda_layer_common/events/__init__.py
b_lambda_layer_common/events/event_bridge_factory.py
b_lambda_layer_common/exceptions/__init__.py
b_lambda_layer_common/exceptions/b_exception.py
b_lambda_layer_common/exceptions/exception_mapper.py
b_lambda_layer_common/exceptions/http_exception.py
b_lambda_layer_common/exceptions/container/__init__.py
b_lambda_layer_common/exceptions/container/already_exists_error.py
b_lambda_layer_common/exceptions/container/bad_request_error.py
b_lambda_layer_common/exceptions/container/conflict_error.py
b_lambda_layer_common/exceptions/container/database_error.py
b_lambda_layer_common/exceptions/container/dependency_error.py
b_lambda_layer_common/exceptions/container/failed_rollback_error.py
b_lambda_layer_common/exceptions/container/forbidden_error.py
b_lambda_layer_common/exceptions/container/internal_error.py
b_lambda_layer_common/exceptions/container/malformed_permission_error.py
b_lambda_layer_common/exceptions/container/malformed_value_error.py
b_lambda_layer_common/exceptions/container/misconfigured_error.py
b_lambda_layer_common/exceptions/container/not_found_error.py
b_lambda_layer_common/exceptions/container/not_reached_error.py
b_lambda_layer_common/exceptions/container/unauthorized_error.py
b_lambda_layer_common/ssm/__init__.py
b_lambda_layer_common/ssm/fetcher.py
b_lambda_layer_common/ssm/refreshable.py
b_lambda_layer_common-4.5.0.dist-info/LICENSE
b_lambda_layer_common-4.5.0.dist-info/METADATA
b_lambda_layer_common-4.5.0.dist-info/WHEEL
b_lambda_layer_common-4.5.0.dist-info/top_level.txt
b_lambda_layer_common-4.5.0.dist-info/RECORD
