Metadata-Version: 2.1
Name: b-lambda-layer-common
Version: 4.5.0
Summary: Common opinionated utilities for every day development.
Home-page: https://github.com/biomapas/B.LambdaLayerCommon.git
License: Apache License 2.0
Keywords: AWS CDK Lambda Layer
Platform: UNKNOWN
Classifier: Programming Language :: Python :: 3
Classifier: Operating System :: OS Independent
